JSModel/Model.py
JSModel/SubModel.py
JSModel/Utilities.py
JSModel/__init__.py
JSModel-0.0.5.dist-info/LICENSE
JSModel-0.0.5.dist-info/METADATA
JSModel-0.0.5.dist-info/WHEEL
JSModel-0.0.5.dist-info/top_level.txt
JSModel-0.0.5.dist-info/RECORD
