Metadata-Version: 2.1
Name: JSModel
Version: 0.0.5
Summary: 'Working with Json data Type easier'
Home-page: https://github.com/tiennguyennesbook/JSModel
Author: Tien Nguyen
Author-email: tien.nguyen@nesbook.io
Classifier: Development Status :: 1 - Planning
Classifier: License :: OSI Approved :: MIT License
Classifier: Intended Audience :: Developers
Classifier: Programming Language :: Python :: 3
Classifier: Operating System :: OS Independent
License-File: LICENSE
